xsocs/__init__.py
xsocs/__main__.py
xsocs/_config.py
xsocs/_app/__init__.py
xsocs/_app/concat.py
xsocs/_app/gui.py
xsocs/examples/__init__.py
xsocs/examples/id01_merge.py
xsocs/examples/id01_peak.py
xsocs/examples/id01_qspace.py
xsocs/gui/Utils.py
xsocs/gui/XsocsGui.py
xsocs/gui/__init__.py
xsocs/gui/gui.py
xsocs/gui/model/Model.py
xsocs/gui/model/ModelDef.py
xsocs/gui/model/Node.py
xsocs/gui/model/NodeEditor.py
xsocs/gui/model/Nodes.py
xsocs/gui/model/TreeView.py
xsocs/gui/model/__init__.py
xsocs/gui/process/FitWidget.py
xsocs/gui/process/MergeWidget.py
xsocs/gui/process/QSpaceWidget.py
xsocs/gui/process/__init__.py
xsocs/gui/project/AcqDataGroup.py
xsocs/gui/project/FitGroup.py
xsocs/gui/project/Hdf5Nodes.py
xsocs/gui/project/IntensityGroup.py
xsocs/gui/project/ProjectDef.py
xsocs/gui/project/ProjectItem.py
xsocs/gui/project/ProjectNodes.py
xsocs/gui/project/QSpaceGroup.py
xsocs/gui/project/ScanPositionsItem.py
xsocs/gui/project/ShiftGroup.py
xsocs/gui/project/XsocsH5Factory.py
xsocs/gui/project/XsocsProject.py
xsocs/gui/project/__init__.py
xsocs/gui/silx_imports/ImageRois.py
xsocs/gui/silx_imports/__init__.py
xsocs/gui/view/FitView.py
xsocs/gui/view/QspaceView.py
xsocs/gui/view/__init__.py
xsocs/gui/view/fitview/DropPlotWidget.py
xsocs/gui/view/fitview/FitModel.py
xsocs/gui/view/fitview/Plotter.py
xsocs/gui/view/fitview/__init__.py
xsocs/gui/view/intensity/IntensityView.py
xsocs/gui/view/intensity/RectRoiWidget.py
xsocs/gui/view/intensity/__init__.py
xsocs/gui/view/shift/ShiftSubject.py
xsocs/gui/view/shift/ShiftView.py
xsocs/gui/view/shift/__init__.py
xsocs/gui/widgets/AcqParamsWidget.py
xsocs/gui/widgets/Buttons.py
xsocs/gui/widgets/Containers.py
xsocs/gui/widgets/FileChooser.py
xsocs/gui/widgets/Input.py
xsocs/gui/widgets/PlotGrabber.py
xsocs/gui/widgets/PointWidget.py
xsocs/gui/widgets/ProjectChooser.py
xsocs/gui/widgets/RoiAxisWidget.py
xsocs/gui/widgets/ScatterPlot.py
xsocs/gui/widgets/Wizard.py
xsocs/gui/widgets/XsocsPlot2D.py
xsocs-2024.9.0.dist-info/LICENSE
xsocs-2024.9.0.dist-info/METADATA
xsocs-2024.9.0.dist-info/WHEEL
xsocs-2024.9.0.dist-info/entry_points.txt
xsocs-2024.9.0.dist-info/top_level.txt
xsocs-2024.9.0.dist-info/RECORD
