Metadata-Version: 2.1
Name: xsocs
Version: 2024.9.0
Summary: Xray Strain Orientation Calculation Software
Author-email: ESRF <silx@esrf.fr>
License: MIT
Project-URL: Homepage, https://gitlab.esrf.fr/kmap/xsocs
Project-URL: Documentation, https://kmap.gitlab-pages.esrf.fr/xsocs/
Classifier: Development Status :: 4 - Beta
Classifier: Environment :: Console
Classifier: Environment :: MacOS X
Classifier: Environment :: Win32 (MS Windows)
Classifier: Environment :: X11 Applications :: Qt
Classifier: Intended Audience :: Education
Classifier: Intended Audience :: Science/Research
Classifier: License :: OSI Approved :: MIT License
Classifier: Natural Language :: English
Classifier: Operating System :: MacOS
Classifier: Operating System :: Microsoft :: Windows
Classifier: Operating System :: POSIX
Classifier: Programming Language :: Python :: 3
Classifier: Topic :: Scientific/Engineering :: Physics
Classifier: Topic :: Software Development :: Libraries :: Python Modules
Requires-Python: >=3.8
License-File: LICENSE
Requires-Dist: numpy
Requires-Dist: h5py
Requires-Dist: fabio
Requires-Dist: silx>=1.0.0
Requires-Dist: xrayutilities
Requires-Dist: scipy
Requires-Dist: setuptools
Requires-Dist: packaging
Provides-Extra: dev
Requires-Dist: black; extra == "dev"
Requires-Dist: build; extra == "dev"
Requires-Dist: flake8; extra == "dev"
Requires-Dist: nbsphinx; extra == "dev"
Requires-Dist: pillow; extra == "dev"
Requires-Dist: setuptools; extra == "dev"
Requires-Dist: Sphinx; extra == "dev"
Requires-Dist: sphinxcontrib.programoutput; extra == "dev"
Requires-Dist: twine; extra == "dev"
Requires-Dist: wheel; extra == "dev"
Provides-Extra: gui
Requires-Dist: PyOpenGL; extra == "gui"
Requires-Dist: matplotlib; extra == "gui"
Requires-Dist: PyQt5; extra == "gui"
